{
  "family": "book-backend-task",
  "networkMode": "awsvpc",
  "requiresCompatibilities": ["FARGATE"],
  "cpu": "512",
  "memory": "1024",
  "executionRoleArn": "arn:aws:iam::<ACCOUNT_ID>:role/ecsTaskExecutionRole",
  "taskRoleArn": "arn:aws:iam::<ACCOUNT_ID>:role/ecsTaskRole",
  "containerDefinitions": [
    {
      "name": "BookBookingSystem",
      "image": "REPLACED_BY_ACTIONS",
      "portMappings": [{ "containerPort": 8080, "protocol": "tcp" }],
      "essential": true,
      "environment": [
        { "name": "SPRING_PROFILES_ACTIVE", "value": "prod" }
      ],
      "logConfiguration": {
        "logDriver": "awslogs",
        "options": {
          "awslogs-group": "/ecs/book-backend",
          "awslogs-region": "ap-south-1",
          "awslogs-stream-prefix": "ecs"
        }
      }
    }
  ]
}
